README.md
setup.cfg
setup.py
timbral_models/Timbral_Booming.py
timbral_models/Timbral_Brightness.py
timbral_models/Timbral_Depth.py
timbral_models/Timbral_Extractor.py
timbral_models/Timbral_Hardness.py
timbral_models/Timbral_Reverb.py
timbral_models/Timbral_Roughness.py
timbral_models/Timbral_Sharpness.py
timbral_models/Timbral_Warmth.py
timbral_models/__init__.py
timbral_models/timbral_util.py
timbral_models/timbral_util_original.py
timbral_models.egg-info/PKG-INFO
timbral_models.egg-info/SOURCES.txt
timbral_models.egg-info/dependency_links.txt
timbral_models.egg-info/not-zip-safe
timbral_models.egg-info/requires.txt
timbral_models.egg-info/top_level.txt